<?xml version="1.0" encoding="UTF-8"?>
<!DOCTYPE mapper PUBLIC "-//mybatis.org//DTD Mapper 3.0//EN" "http://mybatis.org/dtd/mybatis-3-mapper.dtd">
<mapper namespace="com.zakary.qingblog.mapper.UserMapper">
  <resultMap id="BaseResultMap" type="com.zakary.qingblog.domain.User">
    <!--
      WARNING - @mbg.generated
      This element is automatically generated by MyBatis Generator, do not modify.
    -->
    <id column="user_id" jdbcType="INTEGER" property="userId" />
    <result column="user_name" jdbcType="VARCHAR" property="userName" />
    <result column="user_password" jdbcType="VARCHAR" property="userPassword" />
    <result column="user_tel" jdbcType="VARCHAR" property="userTel" />
    <result column="user_mail" jdbcType="VARCHAR" property="userMail" />
    <result column="user_register_date" jdbcType="DATE" property="userRegisterDate" />
    <result column="user_image" jdbcType="VARCHAR" property="userImage" />
    <result column="user_state" jdbcType="INTEGER" property="userState" />
  </resultMap>
  <delete id="deleteByPrimaryKey" parameterType="java.lang.Integer">
    <!--
      WARNING - @mbg.generated
      This element is automatically generated by MyBatis Generator, do not modify.
    -->
    delete from user
    where user_id = #{userId,jdbcType=INTEGER}
  </delete>
  <insert id="insert" parameterType="com.zakary.qingblog.domain.User">
    <!--
      WARNING - @mbg.generated
      This element is automatically generated by MyBatis Generator, do not modify.
    -->
    insert into user (user_name, user_password,
      user_tel, user_mail, user_register_date, 
      user_image, user_state)
    values (#{userName,jdbcType=VARCHAR}, #{userPassword,jdbcType=VARCHAR},
      #{userTel,jdbcType=VARCHAR}, #{userMail,jdbcType=VARCHAR}, #{userRegisterDate,jdbcType=DATE},
      #{userImage,jdbcType=VARCHAR}, #{userState,jdbcType=INTEGER})
  </insert>
  <update id="updateByPrimaryKey" parameterType="com.zakary.qingblog.domain.User">
    <!--
      WARNING - @mbg.generated
      This element is automatically generated by MyBatis Generator, do not modify.
    -->
    update user
    set user_name = #{userName,jdbcType=VARCHAR},
      user_password = #{userPassword,jdbcType=VARCHAR},
      user_tel = #{userTel,jdbcType=VARCHAR},
      user_mail = #{userMail,jdbcType=VARCHAR},
      user_register_date = #{userRegisterDate,jdbcType=DATE},
      user_image = #{userImage,jdbcType=VARCHAR},
      user_state = #{userState,jdbcType=INTEGER}
    where user_id = #{userId,jdbcType=INTEGER}
  </update>
  <select id="selectByPrimaryKey" parameterType="java.lang.Integer" resultMap="BaseResultMap">
    <!--
      WARNING - @mbg.generated
      This element is automatically generated by MyBatis Generator, do not modify.
    -->
    select user_id, user_name, user_password, user_tel, user_mail, user_register_date,
    user_image, user_state
    from user
    where user_id = #{userId,jdbcType=INTEGER}
  </select>
  <select id="selectAll" resultMap="BaseResultMap">
    <!--
      WARNING - @mbg.generated
      This element is automatically generated by MyBatis Generator, do not modify.
    -->
    select user_id, user_name, user_password, user_tel, user_mail, user_register_date,
    user_image, user_state
    from user
  </select>
  <select id="selectByUserMail" parameterType="java.lang.String" resultType="com.zakary.qingblog.domain.User">
    select user_id, user_name, user_password, user_tel, user_mail, user_register_date,
    user_image, user_state
    from user
    where user_mail = #{userMail,jdbcType=VARCHAR}
  </select>
  <select id="selectCountByUserMail" parameterType="java.lang.String" resultType="java.lang.Integer">
    select count(*)
    from user
    where user_mail = #{userMail,jdbcType=VARCHAR}
  </select>
  <select id="selectAllCount" resultType="java.lang.Integer">
    select count(*)
    from user
  </select>
  <update id="updateProfile">
    update user
    set user_image=#{id,jdbcType=VARCHAR}
    where user_id=#{userId,jdbcType=INTEGER}
  </update>
</mapper>